udpcp/__init__.py
udpcp/_version.py
udpcp/protocol/__init__.py
udpcp/protocol/checksum_mode.py
udpcp/protocol/message_type.py
udpcp/protocol/packet.py
udpcp/protocol/transfer_mode.py
udpcp/protocol/_utils/__init__.py
udpcp/protocol/_utils/specification.py
udpcp-0.1.0.dist-info/LICENSE
udpcp-0.1.0.dist-info/METADATA
udpcp-0.1.0.dist-info/WHEEL
udpcp-0.1.0.dist-info/top_level.txt
udpcp-0.1.0.dist-info/RECORD
